f1_report_by_viacent/__init__.py
f1_report_by_viacent/cli.py
f1_report_by_viacent/functions.py
f1_report_by_viacent-0.1.4.dist-info/METADATA
f1_report_by_viacent-0.1.4.dist-info/WHEEL
f1_report_by_viacent-0.1.4.dist-info/entry_points.txt
f1_report_by_viacent-0.1.4.dist-info/licenses/LICENSE
f1_report_by_viacent-0.1.4.dist-info/RECORD
