Metadata-Version: 2.4
Name: f1_report_by_viacent
Version: 0.1.4
Summary: Program for generating report for Formula 1 race - Monaco 2018
Author-email: Oleksandr Khomiarchuk <akhomyarchuk@gmail.com>
License: MIT License
License-File: LICENSE
